{
  "themes": {
    "global": {
      "label": "世界をつなぐビジネス",
      "shortLabel": "国際・グローバル",
      "route": "グローバルリーダー学修コース",
      "lead": "国境を越える課題や多様な価値観に向き合い、世界で価値を生み出す学びと相性がよさそうです。",
      "points": [
        "グローバル経済や国際比較経営史を学ぶ",
        "GLOBEで実践的な英語力を磨く",
        "海外研修・留学も視野に入れる"
      ],
      "staffPrompt": "英語で学ぶ機会や海外研修について聞いてみよう。"
    },
    "business": {
      "label": "アイデアを事業にする力",
      "shortLabel": "ビジネスデザイン",
      "route": "ビジネスデザイン学修コース",
      "lead": "人や社会の「こうだったらいい」を、商品・サービス・組織の仕組みに変えていく力が光ります。",
      "points": [
        "マーケティングや経営戦略を学ぶ",
        "組織マネジメント・ダイバーシティを探究",
        "HLPのワークショップで課題解決を実践"
      ],
      "staffPrompt": "企業・地域の課題に取り組む授業やゼミの話を聞いてみよう。"
    },
    "finance": {
      "label": "お金の流れから未来を読む力",
      "shortLabel": "金融・財務",
      "route": "金融・財務プロフェッショナル学修コース",
      "lead": "数字の裏側にある社会や企業の動きを読み解き、意思決定を支える学びが似合いそうです。",
      "points": [
        "会計学・財務管理論・金融論を学ぶ",
        "企業価値や資金の流れを考える",
        "簿記・FP・証券アナリストなどの学びへ"
      ],
      "staffPrompt": "資格学習と専門授業をどう両立できるか聞いてみよう。"
    },
    "social": {
      "label": "社会課題を、前に進める力",
      "shortLabel": "政策・地域・SDGs",
      "route": "ビジネスデザイン学修コース",
      "lead": "地域、環境、貧困・格差などの課題を、経済とビジネスの両方から解く学びがぴったりです。",
      "points": [
        "ポリシー・デザインを通じて政策を考える",
        "サステナビリティ＆地域共創を探究",
        "貧困・開発や気候変動の経済学に触れる"
      ],
      "staffPrompt": "地域・環境・国際協力をテーマにした学びを聞いてみよう。"
    },
    "data": {
      "label": "データで次の一手を選ぶ力",
      "shortLabel": "データサイエンス",
      "route": "ビジネスデザイン学修コース",
      "lead": "感覚だけに頼らず、データを手がかりに新しい商品・政策・仕組みを考える学びに向いています。",
      "points": [
        "統計の基礎からデータ解析力を磨く",
        "ソーシャル・データサイエンスを学ぶ",
        "ビジネスや社会課題の解決に活かす"
      ],
      "staffPrompt": "高校までの数学経験に関わらず学べるか、具体的に聞いてみよう。"
    },
    "leadership": {
      "label": "人の力を引き出すリーダーシップ",
      "shortLabel": "リーダーシップ",
      "route": "ヒューマニスティック・リーダーシップ（HLP）",
      "lead": "誰かを一方的に引っ張るよりも、互いの個性を活かしてチームで前に進む力を伸ばせそうです。",
      "points": [
        "少人数の実践型ワークショップに挑戦",
        "地域・企業課題の解決に取り組む",
        "自分らしいリーダーシップを見つける"
      ],
      "staffPrompt": "HLPで実際に取り組むテーマや雰囲気を聞いてみよう。"
    }
  },
  "questions": [
    {
      "id": "interest",
      "type": "multi",
      "max": 2,
      "title": "今、いちばん気になるテーマは？",
      "helper": "「少し気になる」でも大丈夫。最大2つ選んでください。",
      "choices": [
        [
          "global",
          "世界とつながる仕事",
          "海外・異文化・国際協力"
        ],
        [
          "business",
          "新しい商品やサービス",
          "企画・起業・マーケティング"
        ],
        [
          "finance",
          "お金と企業のしくみ",
          "会計・投資・金融"
        ],
        [
          "social",
          "社会や地域の課題",
          "環境・貧困・地方創生"
        ],
        [
          "data",
          "データで考えること",
          "統計・AI・分析"
        ],
        [
          "leadership",
          "人やチームを動かすこと",
          "組織・対話・リーダーシップ"
        ]
      ]
    },
    {
      "id": "scene",
      "type": "single",
      "title": "どんな場面で「力になりたい」と思う？",
      "helper": "直感で1つ選んでください。",
      "choices": [
        [
          "business,leadership",
          "仲間とアイデアを形にするとき",
          "企画を立てて、みんなで実現したい"
        ],
        [
          "social,global",
          "社会の困りごとに向き合うとき",
          "地域や世界の課題を前に進めたい"
        ],
        [
          "finance,data",
          "複雑な情報から答えを見つけるとき",
          "数字や事実をもとに考えたい"
        ],
        [
          "global,leadership",
          "違う考えの人と協力するとき",
          "多様な人と一緒に挑戦したい"
        ]
      ]
    },
    {
      "id": "method",
      "type": "single",
      "title": "学び方として、わくわくするのは？",
      "helper": "今の得意・不得意ではなく、これからやってみたい方を選んでください。",
      "choices": [
        [
          "data,finance",
          "数字やデータを読み解く",
          "根拠を見つけて、納得できる答えを出したい"
        ],
        [
          "business,social",
          "現場の声を聞いて解決策を考える",
          "人や地域のリアルを大切にしたい"
        ],
        [
          "global,leadership",
          "対話や英語で視野を広げる",
          "違いを知り、新しい見方を得たい"
        ],
        [
          "business,leadership",
          "チームで試しながら学ぶ",
          "役割を分けて、一緒に完成させたい"
        ]
      ]
    },
    {
      "id": "future",
      "type": "single",
      "title": "将来、どんな自分になっていたらうれしい？",
      "helper": "職業が決まっていなくても大丈夫です。",
      "choices": [
        [
          "global",
          "世界を舞台に働いている",
          "海外企業・国際協力・留学など"
        ],
        [
          "business",
          "新しい価値を生み出している",
          "商品開発・企画・起業など"
        ],
        [
          "finance",
          "組織の大事な判断を支えている",
          "会計・金融・経営管理など"
        ],
        [
          "social",
          "誰かの暮らしを良くしている",
          "地域・環境・公共政策など"
        ],
        [
          "data",
          "情報を活かして変化をつくっている",
          "分析・IT・マーケティングなど"
        ],
        [
          "leadership",
          "チームの可能性を広げている",
          "組織づくり・人材・プロジェクトなど"
        ]
      ]
    },
    {
      "id": "value",
      "type": "single",
      "title": "大切にしたい価値観に近いのは？",
      "helper": "正解はありません。今の気持ちに近いものを選んでください。",
      "choices": [
        [
          "social,leadership",
          "人の幸せや、よりよい社会に役立ちたい",
          "自分だけでなく、周りの人にも目を向けたい"
        ],
        [
          "global",
          "違いを楽しみ、視野を広げ続けたい",
          "新しい文化や考え方にふれて成長したい"
        ],
        [
          "business",
          "まずやってみて、形にしていきたい",
          "アイデアを行動へ移したい"
        ],
        [
          "finance,data",
          "事実に基づいて、よりよい選択をしたい",
          "数字や仕組みを味方につけたい"
        ]
      ]
    },
    {
      "id": "challenge",
      "type": "single",
      "title": "大学で、最初に挑戦してみたいことは？",
      "helper": "まだ迷っている人は「人と協力」を選んでみてください。",
      "choices": [
        [
          "leadership,business",
          "企業や地域の課題をチームで解決する",
          "実践型ワークショップに挑戦したい"
        ],
        [
          "global",
          "英語で学び、海外にも目を向ける",
          "研修や留学にチャレンジしたい"
        ],
        [
          "finance,data",
          "専門性を磨き、資格や分析力を身につける",
          "将来に役立つ武器をつくりたい"
        ],
        [
          "social",
          "気候変動や地域などのテーマを深く探究する",
          "気になる社会課題を学びたい"
        ]
      ]
    }
  ]
}
